MANIFEST.in
gitbranch
gitversion
setup.py
rsbag/__init__.py
rsbag/version.py.in
rsbag_python.egg-info/PKG-INFO
rsbag_python.egg-info/SOURCES.txt
rsbag_python.egg-info/dependency_links.txt
rsbag_python.egg-info/requires.txt
rsbag_python.egg-info/top_level.txt