Metadata-Version: 1.1
Name: rsbag-python
Version: 0.17.1
Summary: Client API for RSBag
Home-page: https://code.cor-lab.org/projects/rsbag
Author: Jan Moringen
Author-email: jmoringe@techfak.uni-bielefeld.de
License: LGPLv3+
Keywords: middleware,study,logging,robotics
Platform: UNKNOWN
Classifier: Programming Language :: Python
Classifier: Development Status :: 5 - Production/Stable
Classifier: Environment :: Other Environment
Classifier: Intended Audience :: Developers
Classifier: Intended Audience :: Science/Research
Classifier: License :: OSI Approved :: GNU Library or Lesser General Public License (LGPL)
Classifier: Operating System :: OS Independent
Classifier: Topic :: Communications
Classifier: Topic :: Scientific/Engineering
Classifier: Topic :: Software Development :: Libraries
Classifier: Topic :: Software Development :: Libraries :: Python Modules
